wadas_runtime/.gitignore
wadas_runtime/__init__.py
wadas_runtime/_core.cp310-win_amd64.pyd
wadas_runtime/_version.py
wadas_runtime-0.2.6.dist-info/METADATA
wadas_runtime-0.2.6.dist-info/WHEEL
wadas_runtime-0.2.6.dist-info/RECORD
