Metadata-Version: 2.1
Name: wadas_runtime
Version: 0.2.6
Summary: Wadas Inference Runtime
Keywords: intel core ultra,wadas,inference,runtime,openvino
Author-Email: Alessandro Palla <alessandro.palla@intel.com>
Classifier: Development Status :: 4 - Beta
Classifier: License :: OSI Approved :: MIT License
Classifier: Programming Language :: Python :: 3 :: Only
Classifier: Programming Language :: Python :: 3.10
Classifier: Programming Language :: Python :: 3.11
Classifier: Programming Language :: Python :: 3.12
Classifier: Programming Language :: Python :: 3.13
Project-URL: Homepage, https://github.com/stefanodellosa-personal/wadas-runtime
Requires-Python: >=3.10
Requires-Dist: openvino==2025.1
Requires-Dist: hwid
Requires-Dist: requests
Provides-Extra: dev
Requires-Dist: pytest; extra == "dev"
Requires-Dist: cryptography; extra == "dev"
Requires-Dist: build; extra == "dev"
Requires-Dist: cibuildwheel; extra == "dev"
Requires-Dist: twine; extra == "dev"
